litsense_wrapper.py
litsense_wrapper-0.1.1.dist-info/licenses/LICENSE
litsense_wrapper-0.1.1.dist-info/METADATA
litsense_wrapper-0.1.1.dist-info/WHEEL
litsense_wrapper-0.1.1.dist-info/top_level.txt
litsense_wrapper-0.1.1.dist-info/RECORD
