Metadata-Version: 2.4
Name: litsense-wrapper
Version: 0.1.1
Summary: Lightweight Python wrapper for the NCBI LitSense2 API
Author: Dinh Long Huynh
License-Expression: MIT
Project-URL: Homepage, https://github.com/DinhLongHuynh/LitSense_Wrapper
Project-URL: Repository, https://github.com/DinhLongHuynh/LitSense_Wrapper
Project-URL: Documentation, https://www.ncbi.nlm.nih.gov/research/litsense2/
Project-URL: Issues, https://github.com/DinhLongHuynh/LitSense_Wrapper/issues
Keywords: litsense,ncbi,biomedical,nlp,api
Classifier: Programming Language :: Python :: 3
Classifier: Operating System :: OS Independent
Classifier: Topic :: Scientific/Engineering :: Bio-Informatics
Requires-Python: >=3.9
License-File: LICENSE
Requires-Dist: requests>=2.28.0
Dynamic: license-file
